CONTRIBUTING.md
LICENSE
MANIFEST.in
README.md
setup.cfg
setup.py
django_opensearch_dsl/__init__.py
django_opensearch_dsl/apps.py
django_opensearch_dsl/documents.py
django_opensearch_dsl/exceptions.py
django_opensearch_dsl/fields.py
django_opensearch_dsl/models.py
django_opensearch_dsl/registries.py
django_opensearch_dsl/search.py
django_opensearch_dsl/signals.py
django_opensearch_dsl.egg-info/PKG-INFO
django_opensearch_dsl.egg-info/SOURCES.txt
django_opensearch_dsl.egg-info/dependency_links.txt
django_opensearch_dsl.egg-info/requires.txt
django_opensearch_dsl.egg-info/top_level.txt
django_opensearch_dsl/management/__init__.py
django_opensearch_dsl/management/enums.py
django_opensearch_dsl/management/types.py
django_opensearch_dsl/management/commands/__init__.py
django_opensearch_dsl/management/commands/opensearch.py
docs/CHANGELOG.md