Metadata-Version: 2.1
Name: django-opensearch-dsl
Version: 0.3.0
Summary: Wrapper around opensearch-dsl-py for django models
Home-page: https://github.com/qcoumes/django-opensearch-dsl
Author: Quentin Coumes (Codoc)
Author-email: coumes.quentin@gmail.com
License: Apache Software License 2.0
Keywords: django elasticsearch elasticsearch-dsl opensearch opensearch-dsl
Platform: UNKNOWN
Classifier: Development Status :: 4 - Beta
Classifier: Framework :: Django
Classifier: Framework :: Django :: 2.1
Classifier: Framework :: Django :: 2.2
Classifier: Framework :: Django :: 3.0
Classifier: Framework :: Django :: 3.1
Classifier: Framework :: Django :: 3.2
Classifier: Framework :: Django :: 4.0
Classifier: Intended Audience :: Developers
Classifier: License :: OSI Approved :: Apache Software License
Classifier: Natural Language :: English
Classifier: Programming Language :: Python :: 3
Classifier: Programming Language :: Python :: 3.6
Classifier: Programming Language :: Python :: 3.7
Classifier: Programming Language :: Python :: 3.8
Classifier: Programming Language :: Python :: 3.9
Classifier: Programming Language :: Python :: 3.10
License-File: LICENSE
